README.md
wirikiki/__init__.py
wirikiki/authentication.py
wirikiki/cli/__init__.py
wirikiki/cli/wirikiki.py
wirikiki/cli/wirikiki_pwgen.py
wirikiki/config/settings.toml
wirikiki/config/users.db
wirikiki/configuration.py
wirikiki/models.py
wirikiki/myKB/.git/COMMIT_EDITMSG
wirikiki/myKB/.git/HEAD
wirikiki/myKB/.git/config
wirikiki/myKB/.git/description
wirikiki/myKB/.git/hooks/applypatch-msg.sample
wirikiki/myKB/.git/hooks/commit-msg.sample
wirikiki/myKB/.git/hooks/fsmonitor-watchman.sample
wirikiki/myKB/.git/hooks/post-update.sample
wirikiki/myKB/.git/hooks/pre-applypatch.sample
wirikiki/myKB/.git/hooks/pre-commit.sample
wirikiki/myKB/.git/hooks/pre-merge-commit.sample
wirikiki/myKB/.git/hooks/pre-push.sample
wirikiki/myKB/.git/hooks/pre-rebase.sample
wirikiki/myKB/.git/hooks/pre-receive.sample
wirikiki/myKB/.git/hooks/prepare-commit-msg.sample
wirikiki/myKB/.git/hooks/push-to-checkout.sample
wirikiki/myKB/.git/hooks/update.sample
wirikiki/myKB/.git/index
wirikiki/myKB/.git/info/exclude
wirikiki/myKB/.git/logs/HEAD
wirikiki/myKB/.git/logs/refs/heads/master
wirikiki/myKB/.git/objects/02/4380be7c2ace9645e69d1042dec74641c6492e
wirikiki/myKB/.git/objects/07/d0b117b0f5418f91ae648bfb798e6c1f2f7d65
wirikiki/myKB/.git/objects/16/8d32e8561e6195f3837ab2c71cb569b1fc486b
wirikiki/myKB/.git/objects/16/9e6117abef0c7b21061c632f4dcdaefd60ae50
wirikiki/myKB/.git/objects/23/0178acfa96f5b3766a56e7b6988caade40c7ff
wirikiki/myKB/.git/objects/25/2e0d778933f460b1c129e8ef4dbb4cad6dde80
wirikiki/myKB/.git/objects/35/702f8138a4f280c8f678d890f511a8e4aca6c5
wirikiki/myKB/.git/objects/36/c7fe7c069cad08ae006a220afe6051c034b035
wirikiki/myKB/.git/objects/38/7629de8687ba9321fd59736f9f3fa78ea2fb96
wirikiki/myKB/.git/objects/42/b15b936c877dbd4f12013d7b9a03eba0d8c45c
wirikiki/myKB/.git/objects/5b/cc8a884a2cfabc3864955253eec70ab4a73e03
wirikiki/myKB/.git/objects/5d/83e0bc09aa3b0d3bca2d69adf1dfe4b42077d9
wirikiki/myKB/.git/objects/78/8c6c300d4ee42ef54d598372e0f15fdc54c7fb
wirikiki-1.1.2.dist-info/entry_points.txt
wirikiki-1.1.2.dist-info/WHEEL
wirikiki-1.1.2.dist-info/METADATA
wirikiki-1.1.2.dist-info/RECORD
