Metadata-Version: 2.1
Name: wirikiki
Version: 1.1.2
Summary: A tiny desktop wiki
Home-page: http://github.com/fdev31/wirikiki/
Author: fdev31
Author-email: fdev31@gmail.com
Requires-Python: >=3.10,<4.0
Classifier: Programming Language :: Python :: 3
Classifier: Programming Language :: Python :: 3.10
Requires-Dist: aiofiles (>=0.8.0,<0.9.0)
Requires-Dist: fastapi (>=0.79.0,<0.80.0)
Requires-Dist: orjson (>=3.7.11,<4.0.0)
Requires-Dist: python-jose (>=3.3.0,<4.0.0)
Requires-Dist: python-multipart (>=0.0.5,<0.0.6)
Requires-Dist: setproctitle (>=1.3.0,<2.0.0)
Requires-Dist: tomli (>=2.0.1,<3.0.0)
Requires-Dist: uvicorn (>=0.18.2,<0.19.0)
